floatcsep/__init__.py
floatcsep/evaluation.py
floatcsep/experiment.py
floatcsep/model.py
floatcsep/commands/__init__.py
floatcsep/commands/main.py
floatcsep/infrastructure/__init__.py
floatcsep/infrastructure/engine.py
floatcsep/infrastructure/environments.py
floatcsep/infrastructure/logger.py
floatcsep/infrastructure/registries.py
floatcsep/infrastructure/repositories.py
floatcsep/postprocess/__init__.py
floatcsep/postprocess/plot_handler.py
floatcsep/postprocess/reporting.py
floatcsep/postprocess/artifacts/NotoSans-Bold.ttf
floatcsep/postprocess/artifacts/NotoSans-Regular.ttf
floatcsep/postprocess/artifacts/csep_logo.png
floatcsep/postprocess/artifacts/geoinquire_logo.png
floatcsep/postprocess/artifacts/github_logo.png
floatcsep/postprocess/artifacts/logo.png
floatcsep/postprocess/artifacts/readthedocs_logo.png
floatcsep/postprocess/panel/__init__.py
floatcsep/postprocess/panel/app.py
floatcsep/postprocess/panel/layout.py
floatcsep/postprocess/panel/manifest.py
floatcsep/postprocess/panel/views/cats.py
floatcsep/postprocess/panel/views/exp.py
floatcsep/postprocess/panel/views/forecasts.py
floatcsep/postprocess/panel/views/results.py
floatcsep/postprocess/panel/views/utils.py
floatcsep/utils/__init__.py
floatcsep/utils/accessors.py
floatcsep/utils/file_io.py
floatcsep/utils/helpers.py
floatcsep-0.4.6.dist-info/licenses/LICENSE
floatcsep-0.4.6.dist-info/METADATA
floatcsep-0.4.6.dist-info/WHEEL
floatcsep-0.4.6.dist-info/entry_points.txt
floatcsep-0.4.6.dist-info/top_level.txt
floatcsep-0.4.6.dist-info/RECORD
