Metadata-Version: 2.4
Name: floatcsep
Version: 0.4.6
Summary: CSEP Floating Experiment application
Author-email: Pablo Iturrieta <pciturri@gfz-potsdam.de>
License-Expression: BSD-3-Clause
Project-URL: Homepage, https://github.com/cseptesting/floatcsep.git
Keywords: earthquake,forecasting,seismology,CSEP
Classifier: Programming Language :: Python :: 3
Classifier: Programming Language :: Python :: 3.9
Classifier: Programming Language :: Python :: 3.10
Classifier: Programming Language :: Python :: 3.11
Classifier: Programming Language :: Python :: 3.12
Requires-Python: <3.13,>=3.9
License-File: LICENSE
Requires-Dist: numpy
Requires-Dist: dateparser
Requires-Dist: docker
Requires-Dist: gitpython
Requires-Dist: h5py
Requires-Dist: matplotlib
Requires-Dist: pandas
Requires-Dist: panel
Requires-Dist: packaging
Requires-Dist: pycsep
Requires-Dist: pyyaml
Requires-Dist: requests
Requires-Dist: scipy
Requires-Dist: seaborn
Requires-Dist: tables
Requires-Dist: xmltodict
Requires-Dist: weasyprint
Requires-Dist: markdown-it-py
Provides-Extra: dev
Requires-Dist: black; extra == "dev"
Requires-Dist: flake8; extra == "dev"
Requires-Dist: pytest; extra == "dev"
Requires-Dist: pytest-cov; extra == "dev"
Requires-Dist: sphinx; extra == "dev"
Requires-Dist: sphinx-autoapi; extra == "dev"
Requires-Dist: sphinx_design; extra == "dev"
Requires-Dist: sphinx-toolbox; extra == "dev"
Requires-Dist: sphinx-gallery; extra == "dev"
Requires-Dist: sphinx-rtd-theme; extra == "dev"
Requires-Dist: sphinx_copybutton; extra == "dev"
Requires-Dist: vcrpy; extra == "dev"
Dynamic: license-file
